mcp_clp_server/__init__.py
mcp_clp_server/app.py
mcp_clp_server/main.py
mcp_clp_server/server.py
mcp_clp_server-0.1.5.dist-info/METADATA
mcp_clp_server-0.1.5.dist-info/WHEEL
mcp_clp_server-0.1.5.dist-info/entry_points.txt
mcp_clp_server-0.1.5.dist-info/RECORD
