Metadata-Version: 2.4
Name: mcp-clp-server
Version: 0.1.5
Summary: Add your description here
Requires-Python: >=3.12
Requires-Dist: fastmcp>=2.3.4
Requires-Dist: psutil>=7.0.0
